stricture/__init__.py
stricture/cli.py
stricture/commandstricture.py
stricture/exceptions.py
stricture/processstricture.py
stricture/schedule.py
stricture/sfm.py
stricture/stricture.py
Stricture-1.0.8.dist-info/LICENSE
Stricture-1.0.8.dist-info/METADATA
Stricture-1.0.8.dist-info/WHEEL
Stricture-1.0.8.dist-info/entry_points.txt
Stricture-1.0.8.dist-info/top_level.txt
Stricture-1.0.8.dist-info/RECORD
