Metadata-Version: 2.1
Name: Stricture
Version: 1.0.8
Summary: Stricture is a python package that provides classes and a CLI tool for easy scheduling, automating, and managing of specific operations.
Home-page: https://github.com/moorejacob2017/Stricture/
Author: Jacob Moore
Author-email: moorejacob2017@gmail.com
License: MIT
Keywords: automation task job management date time cron schedule scheduling bash process pid command bash week month
Classifier: License :: OSI Approved :: MIT License
Classifier: Programming Language :: Python :: 3
Classifier: Operating System :: POSIX :: Linux
License-File: LICENSE
Requires-Dist: python-dateutil
Requires-Dist: tzlocal
Requires-Dist: argparse
Requires-Dist: psutil
Requires-Dist: pytz
Requires-Dist: PyYAML
Requires-Dist: freezegun
